alfred3_dbtools/__init__.py
alfred3_dbtools/_version.py
alfred3_dbtools/mongotools.py
tests/__init__.py
tests/test_mongotools.py
alfred3_dbtools-0.1.4.dist-info/LICENSE
alfred3_dbtools-0.1.4.dist-info/METADATA
alfred3_dbtools-0.1.4.dist-info/WHEEL
alfred3_dbtools-0.1.4.dist-info/top_level.txt
alfred3_dbtools-0.1.4.dist-info/RECORD
