Metadata-Version: 2.1
Name: alfred3-dbtools
Version: 0.1.4
Summary: A package that provides tools for interacting with databases when working with alfred3 experiments.
Home-page: https://github.com/ctreffe/alfred3-dbtools
Author: Christian Treffenstädt, Johannes Brachem
Author-email: treffenstaedt@psych.uni-goettingen.de
License: UNKNOWN
Platform: UNKNOWN
Classifier: Programming Language :: Python :: 3
Classifier: License :: OSI Approved :: MIT License
Classifier: Operating System :: OS Independent
Requires-Python: >=3.5
Requires-Dist: alfred3 (>=1.1.4)
Requires-Dist: pymongo (>=3.10)
